{
  "kind": "collectionType",
  "collectionName": "site_sections",
  "info": {
    "singularName": "site-section",
    "pluralName": "site-sections",
    "displayName": "Section"
  },
  "options": {
    "draftAndPublish": true
  },
  "pluginOptions": {},
  "attributes": {
    "HeaderLabel": {
      "type": "string",
      "required": true,
      "unique": false
    },
    "NavbarLabel": {
      "type": "string",
      "required": true
    },
    "Pages": {
      "type": "relation",
      "relation": "oneToMany",
      "target": "api::page.page",
      "mappedBy": "Section"
    },
    "URLSlug": {
      "type": "uid",
      "targetField": "HeaderLabel"
    },
    "InternalNotes": {
      "type": "text",
      "private": true
    }
  }
}
